rsshub_twitter_reader/__init__.py
rsshub_twitter_reader/rsshub_twitter_reader.py
rsshub_twitter_reader-0.1.4.dist-info/LICENSE
rsshub_twitter_reader-0.1.4.dist-info/METADATA
rsshub_twitter_reader-0.1.4.dist-info/WHEEL
rsshub_twitter_reader-0.1.4.dist-info/top_level.txt
rsshub_twitter_reader-0.1.4.dist-info/RECORD
