Metadata-Version: 2.2
Name: rsshub_twitter_reader
Version: 0.1.4
Summary: Este projeto permite a leitura de tweets via RSS utilizando o RSSHub
Home-page: https://github.com/dadosnapratica/rsshub_twitter_reader
Author: Flavio Lopes
Author-email: Flavio Lopes <flavio.lopes@ideiasfactory.tech>
License: MIT
Project-URL: Homepage, https://github.com/dadosnapratica/rsshub_twitter_reader
Project-URL: Issues, https://github.com/dadosnapratica/rsshub_twitter_reader/issues
Classifier: Programming Language :: Python :: 3
Classifier: Operating System :: OS Independent
Classifier: License :: OSI Approved :: MIT License
Requires-Python: >=3.6
License-File: LICENSE
Requires-Dist: requests
Requires-Dist: pandas
Requires-Dist: lxml
Dynamic: author
Dynamic: home-page
Dynamic: requires-python
